{"gtabs":[{"panes":[{"ptabs":[{"history":[{"dir":"/Users/svrdlans","file":"albus_to_do.txt","relpos":20,"ts":1664550458},{"dir":"/Users","file":"svrdlans","relpos":3,"ts":1664550458},{"dir":"/Users/svrdlans","file":"openssl","relpos":14,"ts":1664550458},{"dir":"/Users/svrdlans/openssl","file":"..","relpos":0,"ts":1664550458},{"dir":"/Users/svrdlans","file":"..","relpos":0,"ts":1664550458},{"dir":"/Users","file":"svrdlans","relpos":3,"ts":1664550458},{"dir":"/","file":"Users","relpos":4,"ts":1664550458},{"dir":"/Users","file":"svrdlans","relpos":3,"ts":1664550458},{"dir":"/Users/svrdlans","file":"..","relpos":0,"ts":1664550458},{"dir":"/Users","file":"svrdlans","relpos":3,"ts":1664550458},{"dir":"/","file":"Network","relpos":2,"ts":1664550458}],"filters":{"invert":true,"dot":true,"manual":"","auto":""},"last-location":"/","sorting":[2],"preview":false}]},{"ptabs":[{"history":[{"dir":"/Users/svrdlans","file":"..","relpos":0,"ts":1664550458},{"dir":"/Users","file":"svrdlans","relpos":3,"ts":1664550458},{"dir":"/Users/svrdlans","file":"Public","relpos":10,"ts":1664550458},{"dir":"/Users/svrdlans/Public","file":"..","relpos":0,"ts":1664550458},{"dir":"/Users/svrdlans","file":"Movies","relpos":6,"ts":1664550458},{"dir":"/Users/svrdlans/Movies","file":"..","relpos":0,"ts":1664550458},{"dir":"/Users/svrdlans","file":"Movies","relpos":6,"ts":1664550458},{"dir":"/Users/svrdlans/Movies","file":"..","relpos":0,"ts":1664550458},{"dir":"/Users/svrdlans","file":"allan_profiles_companies.csv","relpos":19,"ts":1664550458}],"filters":{"invert":true,"dot":true,"manual":"","auto":""},"last-location":"/Users/svrdlans","sorting":[2],"preview":false}]}],"active-pane":0,"preview":false,"splitter":{"pos":-1,"ratio":0.5,"orientation":"v","expanded":false}}],"marks":{"H":{"dir":"/Users/svrdlans/","file":"..","ts":1664549997},"b":{"dir":"/Users/svrdlans/bin/","file":"..","ts":1664549997},"h":{"dir":"/Users/svrdlans/","file":"..","ts":1664549997},"z":{"dir":"/Users/svrdlans/.config/vifm","file":"..","ts":1664549997}},"bmarks":{},"cmd-hist":[{"text":"help","ts":1664550458},{"text":"quit","ts":1664550458}],"search-hist":[{"text":"movi","ts":1664550458}],"regs":{},"dir-stack":[],"use-term-multiplexer":false}